[{"url": "https://www.waitrose.com/ecom/shop/browse/groceries/frozen/frozen_fruits_and_smoothie_mixes", "category": "300010", "tasks": [{"url": "https://www.waitrose.com/ecom/shop/browse/offers/frozen_offers/frozen_fruits_and_smoothie_mixes_offers", "path": "frozen_fruits_and_smoothie_mixes_offers", "badge": "Frozen Fruits & Smoothie Mixes Offers"}, {"url": "https://www.waitrose.com/ecom/shop/browse/groceries/frozen/frozen_fruits_and_smoothie_mixes/cherries", "path": "cherries", "badge": "Cherries"}, {"url": "https://www.waitrose.com/ecom/shop/browse/groceries/frozen/frozen_fruits_and_smoothie_mixes/blueberry", "path": "blueberry", "badge": "Blueberry"}, {"url": "https://www.waitrose.com/ecom/shop/browse/groceries/frozen/frozen_fruits_and_smoothie_mixes/raspberry", "path": "raspberry", "badge": "Raspberry"}, {"url": "https://www.waitrose.com/ecom/shop/browse/groceries/frozen/frozen_fruits_and_smoothie_mixes/fruit_mix", "path": "fruit_mix", "badge": "Fruit Mix"}, {"url": "https://www.waitrose.com/ecom/shop/browse/groceries/frozen/frozen_fruits_and_smoothie_mixes/strawberry", "path": "strawberry", "badge": "Strawberry"}], "data": [{"__typename": "GridProduct", "searchProduct": {"adTechSponsoredPosition": null, "brand": "Waitrose Ltd", "categories": [{"name": "Groceries", "id": "10051"}, {"name": "Frozen", "id": "300000"}, {"name": "Frozen Fruits & Smoothie Mixes", "id": "300010"}, {"name": "Fruit Mix", "id": "300061"}], "cqResponsive": {"deviceBreakpoints": [{"name": "default", "visible": true, "width": "2"}, {"name": "lg", "visible": true, "width": "3"}, {"name": "md", "visible": true, "width": "4"}, {"name": "sm", "visible": true, "width": "4"}, {"name": "xs", "visible": true, "width": "12"}]}, "crealytics": null, "currentSaleUnitPrice": {"price": {"amount": 2.2, "currencyCode": "GBP"}, "quantity": {"amount": 1, "uom": "C62"}}, "defaultQuantity": {"uom": "C62"}, "depositCharge": null, "displayPrice": "\u00a32.20", "displayPriceEstimated": false, "displayPriceQualifier": "\u00a36.29/kg", "formattedWeightRange": null, "formattedPriceRange": null, "id": "823228-673435-673436", "leadTime": 0, "lineNumber": "823228", "maxPersonalisedMessageLength": 0, "name": "Cooks' Ingredients Frozen Sliced British Bramley Apples", "markedForDelete": false, "persistDefault": true, "productImageUrls": {"extraLarge": "https://ecom-su-static-prod.wtrecom.com/images/products/4/LN_823228_BP_4.jpg", "large": "https://ecom-su-static-prod.wtrecom.com/images/products/11/LN_823228_BP_11.jpg", "medium": "https://ecom-su-static-prod.wtrecom.com/images/products/3/LN_823228_BP_3.jpg", "small": "https://ecom-su-static-prod.wtrecom.com/images/products/9/LN_823228_BP_9.jpg"}, "productType": "G", "promotion": null, "promotions": [], "restriction": {"availableDates": []}, "resultType": "GENERAL", "reviews": {"averageRating": 4.6981, "reviewCount": 53}, "size": "350g", "sponsored": false, "sponsorshipId": null, "substitutionsProhibited": false, "thumbnail": "https://ecom-su-static-prod.wtrecom.com/images/products/9/LN_823228_BP_9.jpg", "typicalWeight": null, "servings": null, "weights": {"uoms": ["C62"], "pricePerUomQualifier": "\u00a36.29/kg", "perUomQualifier": null, "defaultQuantity": null, "servings": null, "sizeDescription": null}, "productTags": [{"name": "Frozen", "tooltip": null}, {"name": "British", "tooltip": null}], "marketingBadges": null}}, {"__typename": "GridProduct", "searchProduct": {"adTechSponsoredPosition": null, "brand": "Waitrose Ltd", "categories": [{"name": "Groceries", "id": "10051"}, {"name": "Frozen", "id": "300000"}, {"name": "Frozen Fruits & Smoothie Mixes", "id": "300010"}, {"name": "Fruit Mix", "id": "300061"}], "cqResponsive": {"deviceBreakpoints": [{"name": "default", "visible": true, "width": "2"}, {"name": "lg", "visible": true, "width": "3"}, {"name": "md", "visible": true, "width": "4"}, {"name": "sm", "visible": true, "width": "4"}, {"name": "xs", "visible": true, "width": "12"}]}, "crealytics": null, "currentSaleUnitPrice": {"price": {"amount": 3.5, "currencyCode": "GBP"}, "quantity": {"amount": 1, "uom": "C62"}}, "defaultQuantity": {"uom": "C62"}, "depositCharge": null, "displayPrice": "\u00a33.50", "displayPriceEstimated": false, "displayPriceQualifier": "\u00a311.67/kg", "formattedWeightRange": null, "formattedPriceRange": null, "id": "717622-101973-101974", "leadTime": 0, "lineNumber": "717622", "maxPersonalisedMessageLength": 0, "name": "Duchy Organic Frozen Berry Mix", "markedForDelete": false, "persistDefault": true, "productImageUrls": {"extraLarge": "https://ecom-su-static-prod.wtrecom.com/images/products/4/LN_717622_BP_4.jpg", "large": "https://ecom-su-static-prod.wtrecom.com/images/products/11/LN_717622_BP_11.jpg", "medium": "https://ecom-su-static-prod.wtrecom.com/images/products/3/LN_717622_BP_3.jpg", "small": "https://ecom-su-static-prod.wtrecom.com/images/products/9/LN_717622_BP_9.jpg"}, "productType": "G", "promotion": null, "promotions": [], "restriction": {"availableDates": []}, "resultType": "GENERAL", "reviews": {"averageRating": 4.6852, "reviewCount": 54}, "size": "300g", "sponsored": false, "sponsorshipId": null, "substitutionsProhibited": false, "thumbnail": "https://ecom-su-static-prod.wtrecom.com/images/products/9/LN_717622_BP_9.jpg", "typicalWeight": null, "servings": null, "weights": {"uoms": ["C62"], "pricePerUomQualifier": "\u00a311.67/kg", "perUomQualifier": null, "defaultQuantity": null, "servings": null, "sizeDescription": null}, "productTags": [{"name": "Frozen", "tooltip": null}], "marketingBadges": []}}, {"__typename": "GridProduct", "searchProduct": {"adTechSponsoredPosition": null, "brand": "Waitrose Ltd", "categories": [{"name": "Groceries", "id": "10051"}, {"name": "Frozen", "id": "300000"}, {"name": "Frozen Fruits & Smoothie Mixes", "id": "300010"}, {"name": "Blueberry", "id": "300058"}], "cqResponsive": {"deviceBreakpoints": [{"name": "default", "visible": true, "width": "2"}, {"name": "lg", "visible": true, "width": "3"}, {"name": "md", "visible": true, "width": "4"}, {"name": "sm", "visible": true, "width": "4"}, {"name": "xs", "visible": true, "width": "12"}]}, "crealytics": null, "currentSaleUnitPrice": {"price": {"amount": 3, "currencyCode": "GBP"}, "quantity": {"amount": 1, "uom": "C62"}}, "defaultQuantity": {"uom": "C62"}, "depositCharge": null, "displayPrice": "\u00a32.40", "displayPriceEstimated": false, "displayPriceQualifier": "\u00a312/kg", "formattedWeightRange": null, "formattedPriceRange": null, "id": "995183-843858-843859", "leadTime": 0, "lineNumber": "995183", "maxPersonalisedMessageLength": 0, "name": "Duchy Organic Frozen Blueberries", "markedForDelete": false, "persistDefault": true, "productImageUrls": {"extraLarge": "https://ecom-su-static-prod.wtrecom.com/images/products/4/LN_995183_BP_4.jpg", "large": "https://ecom-su-static-prod.wtrecom.com/images/products/11/LN_995183_BP_11.jpg", "medium": "https://ecom-su-static-prod.wtrecom.com/images/products/3/LN_995183_BP_3.jpg", "small": "https://ecom-su-static-prod.wtrecom.com/images/products/9/LN_995183_BP_9.jpg"}, "productType": "G", "promotion": {"discount": null, "groups": [{"threshold": 1, "name": "X", "lineNumbers": ["995183"]}], "hidden": null, "myWaitrosePromotion": false, "promotionDescription": "Reduced to Clear", "promotionId": 510760, "promotionTypeCode": "RTC", "wasDisplayPrice": null}, "promotions": [{"discount": null, "groups": [{"threshold": 1, "name": "X", "lineNumbers": ["995183"]}], "hidden": null, "myWaitrosePromotion": false, "promotionDescription": "Reduced to Clear", "promotionId": 510760, "promotionTypeCode": "RTC", "wasDisplayPrice": null}], "restriction": {"availableDates": []}, "resultType": "GENERAL", "reviews": {"averageRating": 4, "reviewCount": 4}, "size": "200g", "sponsored": false, "sponsorshipId": null, "substitutionsProhibited": false, "thumbnail": "https://ecom-su-static-prod.wtrecom.com/images/products/9/LN_995183_BP_9.jpg", "typicalWeight": null, "servings": null, "weights": {"uoms": ["C62"], "pricePerUomQualifier": "\u00a312/kg", "perUomQualifier": null, "defaultQuantity": null, "servings": null, "sizeDescription": null}, "productTags": null, "marketingBadges": []}}, {"__typename": "GridProduct", "searchProduct": {"adTechSponsoredPosition": null, "brand": "Waitrose Ltd", "categories": [{"name": "Groceries", "id": "10051"}, {"name": "Frozen", "id": "300000"}, {"name": "Frozen Fruits & Smoothie Mixes", "id": "300010"}, {"name": "Fruit Mix", "id": "300061"}], "cqResponsive": {"deviceBreakpoints": [{"name": "default", "visible": true, "width": "2"}, {"name": "lg", "visible": true, "width": "3"}, {"name": "md", "visible": true, "width": "4"}, {"name": "sm", "visible": true, "width": "4"}, {"name": "xs", "visible": true, "width": "12"}]}, "crealytics": null, "currentSaleUnitPrice": {"price": {"amount": 4.2, "currencyCode": "GBP"}, "quantity": {"amount": 1, "uom": "C62"}}, "defaultQuantity": {"uom": "C62"}, "depositCharge": null, "displayPrice": "\u00a34.20", "displayPriceEstimated": false, "displayPriceQualifier": "\u00a34.20/kg", "formattedWeightRange": null, "formattedPriceRange": null, "id": "439978-679257-679258", "leadTime": 0, "lineNumber": "439978", "maxPersonalisedMessageLength": 0, "name": "Essential Frozen Berries", "markedForDelete": false, "persistDefault": true, "productImageUrls": {"extraLarge": "https://ecom-su-static-prod.wtrecom.com/images/products/4/LN_439978_BP_4.jpg", "large": "https://ecom-su-static-prod.wtrecom.com/images/products/11/LN_439978_BP_11.jpg", "medium": "https://ecom-su-static-prod.wtrecom.com/images/products/3/LN_439978_BP_3.jpg", "small": "https://ecom-su-static-prod.wtrecom.com/images/products/9/LN_439978_BP_9.jpg"}, "productType": "G", "promotion": null, "promotions": [], "restriction": {"availableDates": []}, "resultType": "GENERAL", "reviews": {"averageRating": 4.6597, "reviewCount": 238}, "size": "1Kg", "sponsored": false, "sponsorshipId": null, "substitutionsProhibited": false, "thumbnail": "https://ecom-su-static-prod.wtrecom.com/images/products/9/LN_439978_BP_9.jpg", "typicalWeight": null, "servings": null, "weights": {"uoms": ["C62"], "pricePerUomQualifier": "\u00a34.20/kg", "perUomQualifier": null, "defaultQuantity": null, "servings": null, "sizeDescription": null}, "productTags": [{"name": "Large pack", "tooltip": null}, {"name": "Frozen", "tooltip": null}], "marketingBadges": []}}, {"__typename": "GridProduct", "searchProduct": {"adTechSponsoredPosition": null, "brand": "Waitrose Ltd", "categories": [{"name": "Groceries", "id": "10051"}, {"name": "Frozen", "id": "300000"}, {"name": "Frozen Fruits & Smoothie Mixes", "id": "300010"}, {"name": "Blueberry", "id": "300058"}], "cqResponsive": {"deviceBreakpoints": [{"name": "default", "visible": true, "width": "2"}, {"name": "lg", "visible": true, "width": "3"}, {"name": "md", "visible": true, "width": "4"}, {"name": "sm", "visible": true, "width": "4"}, {"name": "xs", "visible": true, "width": "12"}]}, "crealytics": null, "currentSaleUnitPrice": {"price": {"amount": 2.85, "currencyCode": "GBP"}, "quantity": {"amount": 1, "uom": "C62"}}, "defaultQuantity": {"uom": "C62"}, "depositCharge": null, "displayPrice": "\u00a32.85", "displayPriceEstimated": false, "displayPriceQualifier": "\u00a37.13/kg", "formattedWeightRange": null, "formattedPriceRange": null, "id": "376067-52962-52963", "leadTime": 0, "lineNumber": "376067", "maxPersonalisedMessageLength": 0, "name": "Essential Frozen Blueberries", "markedForDelete": false, "persistDefault": true, "productImageUrls": {"extraLarge": "https://ecom-su-static-prod.wtrecom.com/images/products/4/LN_376067_BP_4.jpg", "large": "https://ecom-su-static-prod.wtrecom.com/images/products/11/LN_376067_BP_11.jpg", "medium": "https://ecom-su-static-prod.wtrecom.com/images/products/3/LN_376067_BP_3.jpg", "small": "https://ecom-su-static-prod.wtrecom.com/images/products/9/LN_376067_BP_9.jpg"}, "productType": "G", "promotion": {"discount": {"type": "TOTAL_PRICE"}, "groups": [{"threshold": 3, "name": "GROUP1", "lineNumbers": ["376067", "551289", "771268", "832754", "865820", "880866"]}], "hidden": false, "myWaitrosePromotion": false, "promotionDescription": "Add 3 for \u00a36", "promotionId": 93722, "promotionTypeCode": "PMV", "wasDisplayPrice": null}, "promotions": [{"discount": {"type": "TOTAL_PRICE"}, "groups": [{"threshold": 3, "name": "GROUP1", "lineNumbers": ["376067", "551289", "771268", "832754", "865820", "880866"]}], "hidden": false, "myWaitrosePromotion": false, "promotionDescription": "Add 3 for \u00a36", "promotionId": 93722, "promotionTypeCode": "PMV", "wasDisplayPrice": null}], "restriction": {"availableDates": []}, "resultType": "GENERAL", "reviews": {"averageRating": 4.5879, "reviewCount": 580}, "size": "400g", "sponsored": false, "sponsorshipId": null, "substitutionsProhibited": false, "thumbnail": "https://ecom-su-static-prod.wtrecom.com/images/products/9/LN_376067_BP_9.jpg", "typicalWeight": null, "servings": null, "weights": {"uoms": ["C62"], "pricePerUomQualifier": "\u00a37.13/kg", "perUomQualifier": null, "defaultQuantity": null, "servings": null, "sizeDescription": null}, "productTags": [{"name": "Frozen", "tooltip": null}], "marketingBadges": null}}, {"__typename": "GridProduct", "searchProduct": {"adTechSponsoredPosition": null, "brand": "Waitrose Ltd", "categories": [{"name": "Groceries", "id": "10051"}, {"name": "Frozen", "id": "300000"}, {"name": "Frozen Fruits & Smoothie Mixes", "id": "300010"}, {"name": "Cherries", "id": "260676"}], "cqResponsive": {"deviceBreakpoints": [{"name": "default", "visible": true, "width": "2"}, {"name": "lg", "visible": true, "width": "3"}, {"name": "md", "visible": true, "width": "4"}, {"name": "sm", "visible": true, "width": "4"}, {"name": "xs", "visible": true, "width": "12"}]}, "crealytics": null, "currentSaleUnitPrice": {"price": {"amount": 2.85, "currencyCode": "GBP"}, "quantity": {"amount": 1, "uom": "C62"}}, "defaultQuantity": {"uom": "C62"}, "depositCharge": null, "displayPrice": "\u00a32.85", "displayPriceEstimated": false, "displayPriceQualifier": "\u00a37.13/kg", "formattedWeightRange": null, "formattedPriceRange": null, "id": "551289-459695-459696", "leadTime": 0, "lineNumber": "551289", "maxPersonalisedMessageLength": 0, "name": "Essential Frozen Dark Sweet Pitted Cherries", "markedForDelete": false, "persistDefault": true, "productImageUrls": {"extraLarge": "https://ecom-su-static-prod.wtrecom.com/images/products/4/LN_551289_BP_4.jpg", "large": "https://ecom-su-static-prod.wtrecom.com/images/products/11/LN_551289_BP_11.jpg", "medium": "https://ecom-su-static-prod.wtrecom.com/images/products/3/LN_551289_BP_3.jpg", "small": "https://ecom-su-static-prod.wtrecom.com/images/products/9/LN_551289_BP_9.jpg"}, "productType": "G", "promotion": {"discount": {"type": "TOTAL_PRICE"}, "groups": [{"threshold": 3, "name": "GROUP1", "lineNumbers": ["376067", "551289", "771268", "832754", "865820", "880866"]}], "hidden": false, "myWaitrosePromotion": false, "promotionDescription": "Add 3 for \u00a36", "promotionId": 93722, "promotionTypeCode": "PMV", "wasDisplayPrice": null}, "promotions": [{"discount": {"type": "TOTAL_PRICE"}, "groups": [{"threshold": 3, "name": "GROUP1", "lineNumbers": ["376067", "551289", "771268", "832754", "865820", "880866"]}], "hidden": false, "myWaitrosePromotion": false, "promotionDescription": "Add 3 for \u00a36", "promotionId": 93722, "promotionTypeCode": "PMV", "wasDisplayPrice": null}], "restriction": {"availableDates": []}, "resultType": "GENERAL", "reviews": {"averageRating": 4.5287, "reviewCount": 244}, "size": "400g", "sponsored": false, "sponsorshipId": null, "substitutionsProhibited": false, "thumbnail": "https://ecom-su-static-prod.wtrecom.com/images/products/9/LN_551289_BP_9.jpg", "typicalWeight": null, "servings": null, "weights": {"uoms": ["C62"], "pricePerUomQualifier": "\u00a37.13/kg", "perUomQualifier": null, "defaultQuantity": null, "servings": null, "sizeDescription": null}, "productTags": [{"name": "Frozen", "tooltip": null}], "marketingBadges": null}}, {"__typename": "GridProduct", "searchProduct": {"adTechSponsoredPosition": null, "brand": "Waitrose Ltd", "categories": [{"name": "Groceries", "id": "10051"}, {"name": "Frozen", "id": "300000"}, {"name": "Frozen Fruits & Smoothie Mixes", "id": "300010"}, {"name": "Fruit Mix", "id": "300061"}], "cqResponsive": {"deviceBreakpoints": [{"name": "default", "visible": true, "width": "2"}, {"name": "lg", "visible": true, "width": "3"}, {"name": "md", "visible": true, "width": "4"}, {"name": "sm", "visible": true, "width": "4"}, {"name": "xs", "visible": true, "width": "12"}]}, "crealytics": null, "currentSaleUnitPrice": {"price": {"amount": 2.85, "currencyCode": "GBP"}, "quantity": {"amount": 1, "uom": "C62"}}, "defaultQuantity": {"uom": "C62"}, "depositCharge": null, "displayPrice": "\u00a32.85", "displayPriceEstimated": false, "displayPriceQualifier": "\u00a36.34/kg", "formattedWeightRange": null, "formattedPriceRange": null, "id": "865820-679293-679294", "leadTime": 0, "lineNumber": "865820", "maxPersonalisedMessageLength": 0, "name": "Essential Frozen Mango Chunks", "markedForDelete": false, "persistDefault": true, "productImageUrls": {"extraLarge": "https://ecom-su-static-prod.wtrecom.com/images/products/4/LN_865820_BP_4.jpg", "large": "https://ecom-su-static-prod.wtrecom.com/images/products/11/LN_865820_BP_11.jpg", "medium": "https://ecom-su-static-prod.wtrecom.com/images/products/3/LN_865820_BP_3.jpg", "small": "https://ecom-su-static-prod.wtrecom.com/images/products/9/LN_865820_BP_9.jpg"}, "productType": "G", "promotion": {"discount": {"type": "TOTAL_PRICE"}, "groups": [{"threshold": 3, "name": "GROUP1", "lineNumbers": ["376067", "551289", "771268", "832754", "865820", "880866"]}], "hidden": false, "myWaitrosePromotion": false, "promotionDescription": "Add 3 for \u00a36", "promotionId": 93722, "promotionTypeCode": "PMV", "wasDisplayPrice": null}, "promotions": [{"discount": {"type": "TOTAL_PRICE"}, "groups": [{"threshold": 3, "name": "GROUP1", "lineNumbers": ["376067", "551289", "771268", "832754", "865820", "880866"]}], "hidden": false, "myWaitrosePromotion": false, "promotionDescription": "Add 3 for \u00a36", "promotionId": 93722, "promotionTypeCode": "PMV", "wasDisplayPrice": null}], "restriction": {"availableDates": []}, "resultType": "GENERAL", "reviews": {"averageRating": 3.6306, "reviewCount": 111}, "size": "450g", "sponsored": false, "sponsorshipId": null, "substitutionsProhibited": false, "thumbnail": "https://ecom-su-static-prod.wtrecom.com/images/products/9/LN_865820_BP_9.jpg", "typicalWeight": null, "servings": null, "weights": {"uoms": ["C62"], "pricePerUomQualifier": "\u00a36.34/kg", "perUomQualifier": null, "defaultQuantity": null, "servings": null, "sizeDescription": null}, "productTags": [{"name": "Frozen", "tooltip": null}], "marketingBadges": null}}, {"__typename": "GridProduct", "searchProduct": {"adTechSponsoredPosition": null, "brand": "Waitrose Ltd", "categories": [{"name": "Groceries", "id": "10051"}, {"name": "Frozen", "id": "300000"}, {"name": "Frozen Fruits & Smoothie Mixes", "id": "300010"}, {"name": "Fruit Mix", "id": "300061"}], "cqResponsive": {"deviceBreakpoints": [{"name": "default", "visible": true, "width": "2"}, {"name": "lg", "visible": true, "width": "3"}, {"name": "md", "visible": true, "width": "4"}, {"name": "sm", "visible": true, "width": "4"}, {"name": "xs", "visible": true, "width": "12"}]}, "crealytics": null, "currentSaleUnitPrice": {"price": {"amount": 2.85, "currencyCode": "GBP"}, "quantity": {"amount": 1, "uom": "C62"}}, "defaultQuantity": {"uom": "C62"}, "depositCharge": null, "displayPrice": "\u00a32.85", "displayPriceEstimated": false, "displayPriceQualifier": "\u00a35.70/kg", "formattedWeightRange": null, "formattedPriceRange": null, "id": "880866-679299-679300", "leadTime": 0, "lineNumber": "880866", "maxPersonalisedMessageLength": 0, "name": "Essential Frozen Pineapple Chunks", "markedForDelete": false, "persistDefault": true, "productImageUrls": {"extraLarge": "https://ecom-su-static-prod.wtrecom.com/images/products/4/LN_880866_BP_4.jpg", "large": "https://ecom-su-static-prod.wtrecom.com/images/products/11/LN_880866_BP_11.jpg", "medium": "https://ecom-su-static-prod.wtrecom.com/images/products/3/LN_880866_BP_3.jpg", "small": "https://ecom-su-static-prod.wtrecom.com/images/products/9/LN_880866_BP_9.jpg"}, "productType": "G", "promotion": {"discount": {"type": "TOTAL_PRICE"}, "groups": [{"threshold": 3, "name": "GROUP1", "lineNumbers": ["376067", "551289", "771268", "832754", "865820", "880866"]}], "hidden": false, "myWaitrosePromotion": false, "promotionDescription": "Add 3 for \u00a36", "promotionId": 93722, "promotionTypeCode": "PMV", "wasDisplayPrice": null}, "promotions": [{"discount": {"type": "TOTAL_PRICE"}, "groups": [{"threshold": 3, "name": "GROUP1", "lineNumbers": ["376067", "551289", "771268", "832754", "865820", "880866"]}], "hidden": false, "myWaitrosePromotion": false, "promotionDescription": "Add 3 for \u00a36", "promotionId": 93722, "promotionTypeCode": "PMV", "wasDisplayPrice": null}], "restriction": {"availableDates": []}, "resultType": "GENERAL", "reviews": {"averageRating": 4, "reviewCount": 47}, "size": "500g", "sponsored": false, "sponsorshipId": null, "substitutionsProhibited": false, "thumbnail": "https://ecom-su-static-prod.wtrecom.com/images/products/9/LN_880866_BP_9.jpg", "typicalWeight": null, "servings": null, "weights": {"uoms": ["C62"], "pricePerUomQualifier": "\u00a35.70/kg", "perUomQualifier": null, "defaultQuantity": null, "servings": null, "sizeDescription": null}, "productTags": [{"name": "Frozen", "tooltip": null}], "marketingBadges": null}}, {"__typename": "GridProduct", "searchProduct": {"adTechSponsoredPosition": null, "brand": "Waitrose Ltd", "categories": [{"name": "Groceries", "id": "10051"}, {"name": "Frozen", "id": "300000"}, {"name": "Frozen Fruits & Smoothie Mixes", "id": "300010"}, {"name": "Raspberry", "id": "300060"}], "cqResponsive": {"deviceBreakpoints": [{"name": "default", "visible": true, "width": "2"}, {"name": "lg", "visible": true, "width": "3"}, {"name": "md", "visible": true, "width": "4"}, {"name": "sm", "visible": true, "width": "4"}, {"name": "xs", "visible": true, "width": "12"}]}, "crealytics": null, "currentSaleUnitPrice": {"price": {"amount": 2.85, "currencyCode": "GBP"}, "quantity": {"amount": 1, "uom": "C62"}}, "defaultQuantity": {"uom": "C62"}, "depositCharge": null, "displayPrice": "\u00a32.85", "displayPriceEstimated": false, "displayPriceQualifier": "\u00a38.15/kg", "formattedWeightRange": null, "formattedPriceRange": null, "id": "771268-198052-198053", "leadTime": 0, "lineNumber": "771268", "maxPersonalisedMessageLength": 0, "name": "Essential Frozen Raspberries", "markedForDelete": false, "persistDefault": true, "productImageUrls": {"extraLarge": "https://ecom-su-static-prod.wtrecom.com/images/products/4/LN_771268_BP_4.jpg", "large": "https://ecom-su-static-prod.wtrecom.com/images/products/11/LN_771268_BP_11.jpg", "medium": "https://ecom-su-static-prod.wtrecom.com/images/products/3/LN_771268_BP_3.jpg", "small": "https://ecom-su-static-prod.wtrecom.com/images/products/9/LN_771268_BP_9.jpg"}, "productType": "G", "promotion": {"discount": {"type": "TOTAL_PRICE"}, "groups": [{"threshold": 3, "name": "GROUP1", "lineNumbers": ["376067", "551289", "771268", "832754", "865820", "880866"]}], "hidden": false, "myWaitrosePromotion": false, "promotionDescription": "Add 3 for \u00a36", "promotionId": 93722, "promotionTypeCode": "PMV", "wasDisplayPrice": null}, "promotions": [{"discount": {"type": "TOTAL_PRICE"}, "groups": [{"threshold": 3, "name": "GROUP1", "lineNumbers": ["376067", "551289", "771268", "832754", "865820", "880866"]}], "hidden": false, "myWaitrosePromotion": false, "promotionDescription": "Add 3 for \u00a36", "promotionId": 93722, "promotionTypeCode": "PMV", "wasDisplayPrice": null}], "restriction": {"availableDates": []}, "resultType": "GENERAL", "reviews": {"averageRating": 4.5087, "reviewCount": 344}, "size": "350g", "sponsored": false, "sponsorshipId": null, "substitutionsProhibited": false, "thumbnail": "https://ecom-su-static-prod.wtrecom.com/images/products/9/LN_771268_BP_9.jpg", "typicalWeight": null, "servings": null, "weights": {"uoms": ["C62"], "pricePerUomQualifier": "\u00a38.15/kg", "perUomQualifier": null, "defaultQuantity": null, "servings": null, "sizeDescription": null}, "productTags": [{"name": "Frozen", "tooltip": null}], "marketingBadges": null}}, {"__typename": "GridProduct", "searchProduct": {"adTechSponsoredPosition": null, "brand": "Waitrose Ltd", "categories": [{"name": "Groceries", "id": "10051"}, {"name": "Frozen", "id": "300000"}, {"name": "Frozen Fruits & Smoothie Mixes", "id": "300010"}, {"name": "Fruit Mix", "id": "300061"}], "cqResponsive": {"deviceBreakpoints": [{"name": "default", "visible": true, "width": "2"}, {"name": "lg", "visible": true, "width": "3"}, {"name": "md", "visible": true, "width": "4"}, {"name": "sm", "visible": true, "width": "4"}, {"name": "xs", "visible": true, "width": "12"}]}, "crealytics": null, "currentSaleUnitPrice": {"price": {"amount": 2.85, "currencyCode": "GBP"}, "quantity": {"amount": 1, "uom": "C62"}}, "defaultQuantity": {"uom": "C62"}, "depositCharge": null, "displayPrice": "\u00a32.85", "displayPriceEstimated": false, "displayPriceQualifier": "\u00a37.13/kg", "formattedWeightRange": null, "formattedPriceRange": null, "id": "832754-679283-679284", "leadTime": 0, "lineNumber": "832754", "maxPersonalisedMessageLength": 0, "name": "Essential Frozen Strawberries", "markedForDelete": false, "persistDefault": true, "productImageUrls": {"extraLarge": "https://ecom-su-static-prod.wtrecom.com/images/products/4/LN_832754_BP_4.jpg", "large": "https://ecom-su-static-prod.wtrecom.com/images/products/11/LN_832754_BP_11.jpg", "medium": "https://ecom-su-static-prod.wtrecom.com/images/products/3/LN_832754_BP_3.jpg", "small": "https://ecom-su-static-prod.wtrecom.com/images/products/9/LN_832754_BP_9.jpg"}, "productType": "G", "promotion": {"discount": {"type": "TOTAL_PRICE"}, "groups": [{"threshold": 3, "name": "GROUP1", "lineNumbers": ["376067", "551289", "771268", "832754", "865820", "880866"]}], "hidden": false, "myWaitrosePromotion": false, "promotionDescription": "Add 3 for \u00a36", "promotionId": 93722, "promotionTypeCode": "PMV", "wasDisplayPrice": null}, "promotions": [{"discount": {"type": "TOTAL_PRICE"}, "groups": [{"threshold": 3, "name": "GROUP1", "lineNumbers": ["376067", "551289", "771268", "832754", "865820", "880866"]}], "hidden": false, "myWaitrosePromotion": false, "promotionDescription": "Add 3 for \u00a36", "promotionId": 93722, "promotionTypeCode": "PMV", "wasDisplayPrice": null}], "restriction": {"availableDates": []}, "resultType": "GENERAL", "reviews": {"averageRating": 4.3289, "reviewCount": 76}, "size": "400g", "sponsored": false, "sponsorshipId": null, "substitutionsProhibited": false, "thumbnail": "https://ecom-su-static-prod.wtrecom.com/images/products/9/LN_832754_BP_9.jpg", "typicalWeight": null, "servings": null, "weights": {"uoms": ["C62"], "pricePerUomQualifier": "\u00a37.13/kg", "perUomQualifier": null, "defaultQuantity": null, "servings": null, "sizeDescription": null}, "productTags": [{"name": "Frozen", "tooltip": null}], "marketingBadges": null}}, {"__typename": "GridCmsComponent", "aemComponent": {"multiService": false, "multiServiceData": {}, "gridPosition": 10, "resourceType": "waitrosegroceriescms/components/content/tradingcontent/tradingcell", "cqResponsive": {"deviceBreakpoints": [{"width": "12", "name": "xs", "auto": true, "layout": "oneCell", "visible": true}, {"width": "8", "name": "sm", "auto": true, "layout": "twoCell", "visible": true}, {"width": "8", "name": "md", "auto": true, "layout": "twoCell", "visible": true}, {"width": "6", "name": "lg", "auto": true, "layout": "twoCell", "visible": true}, {"width": "4", "name": "default", "auto": true, "layout": "twoCell", "visible": true}]}, "componentId": "_content_waitrosegroceriescms_en_library_productGrid_static-trading-pod_2025_june_bau_tm-1374626-jun25-bau-no1custard_jcr_content_library-par_referenced-component", "uniqueId": "_content_waitrosegroceriescms_en_library_productGrid_static-trading-pod_2025_june_bau_tm-1374626-jun25-bau-no1custard_jcr_content_library-par_referenced-component_10", "childComponents": [], "nodeName": "referenced-component", "componentPlaceholder": false, "styleIds": [], "defaultNumOfCells": "twoCells", "image": {"landscapeImage": {"multiService": false, "multiServiceData": {}, "resourceType": "waitrosegroceriescms/components/content/image", "componentId": "_content_waitrosegroceriescms_en_library_productGrid_static-trading-pod_2025_june_bau_tm-1374626-jun25-bau-no1custard_jcr_content_library-par_referenced-component_image_landscape", "uniqueId": "_content_waitrosegroceriescms_en_library_productGrid_static-trading-pod_2025_june_bau_tm-1374626-jun25-bau-no1custard_jcr_content_library-par_referenced-component_image_landscape", "childComponents": [], "nodeName": "landscape", "componentPlaceholder": false, "styleIds": [], "src": "/content/waitrosegroceriescms/en/library/productGrid/static-trading-pod/2025/june/bau/tm-1374626-jun25-bau-no1custard/jcr:content/library-par/referenced-component/image/landscape.wtrAdaptiveImg.jpg/1750922763198.jpg", "adaptiveSrcs": {}, "altText": "No.1 Milk, Butter, Eggs, Cream & Custard", "uncropped": false, "isDecorative": false, "fileReference": "/content/dam/waitrosegroceriescms/ecomm/2025/june/bau/tm-1374626-Jun25-BAU-No1-Custard-toolkit.jpg", "dynamicImages": {"highQuality90": "https://waitrose-prod.scene7.com/is/image/waitroseprod/tm-1374626-Jun25-BAU-No1-Custard-toolkit?uuid=3d1cbd80-ade1-47dc-a496-3556482f422a&$Waitrose-Image-Preset-90$", "highQuality100": "https://waitrose-prod.scene7.com/is/image/waitroseprod/tm-1374626-Jun25-BAU-No1-Custard-toolkit?uuid=3d1cbd80-ade1-47dc-a496-3556482f422a&$Waitrose-Image-Preset-100$", "highQuality": "https://waitrose-prod.scene7.com/is/image/waitroseprod/tm-1374626-Jun25-BAU-No1-Custard-toolkit?uuid=3d1cbd80-ade1-47dc-a496-3556482f422a&$Waitrose-High-Quality-Image-Preset$", "defaultQuality": "https://waitrose-prod.scene7.com/is/image/waitroseprod/tm-1374626-Jun25-BAU-No1-Custard-toolkit?uuid=3d1cbd80-ade1-47dc-a496-3556482f422a&$Waitrose-Default-Image-Preset$", "highQuality85": "https://waitrose-prod.scene7.com/is/image/waitroseprod/tm-1374626-Jun25-BAU-No1-Custard-toolkit?uuid=3d1cbd80-ade1-47dc-a496-3556482f422a&$Waitrose-Image-Preset-85$", "highQuality95": "https://waitrose-prod.scene7.com/is/image/waitroseprod/tm-1374626-Jun25-BAU-No1-Custard-toolkit?uuid=3d1cbd80-ade1-47dc-a496-3556482f422a&$Waitrose-Image-Preset-95$"}, "analytics": {"promoName": "waitrose:other", "assetModuleType": "Other", "enhancedEcommerceInternalPromotion": false}, "newWindow": false, "mobileImage": {}, "childComponentsVerticalAlignment": "top", "overlayColor": "", "tabletImage": {}, "assetMetadataWidth": "1500", "assetMetadataHeight": "986", ":items": {}, ":itemsOrder": []}, "portraitImage": {"multiService": false, "multiServiceData": {}, "resourceType": "waitrosegroceriescms/components/content/image", "componentId": "_content_waitrosegroceriescms_en_library_productGrid_static-trading-pod_2025_june_bau_tm-1374626-jun25-bau-no1custard_jcr_content_library-par_referenced-component_image_portrait", "uniqueId": "_content_waitrosegroceriescms_en_library_productGrid_static-trading-pod_2025_june_bau_tm-1374626-jun25-bau-no1custard_jcr_content_library-par_referenced-component_image_portrait", "childComponents": [], "nodeName": "portrait", "componentPlaceholder": false, "styleIds": [], "adaptiveSrcs": {}, "uncropped": false, "isDecorative": false, "analytics": {"promoName": "waitrose:other", "assetModuleType": "Other", "enhancedEcommerceInternalPromotion": false}, "newWindow": false, "mobileImage": {}, "childComponentsVerticalAlignment": "top", "overlayColor": "", "tabletImage": {}, ":items": {}, ":itemsOrder": []}}, "textArea": {"heading": "Rich and creamy No.1 dairy", "subheading": "For the best tasting vanilla-speckled custard, cream-topped milk and traditionally made Greek yogurt, it has to be No.1.", "disclaimer": "on selected lines only", "displayDisclaimer": false, "buttonStyle": "primary", "link": {"text": "Shop now", "altText": "Shop now", "url": "/ecom/shop/browse/groceries/fresh_and_chilled/milk_butter_and_eggs/no1_milk_butter_and_eggs", "newWindow": false}, "theme": "light"}, "icons": {"messageIcon": {"display": false}, "brandIcon": {"display": false, "image": {"multiService": false, "multiServiceData": {}, "resourceType": "waitrosegroceriescms/components/content/image", "componentId": "_content_waitrosegroceriescms_en_library_productGrid_static-trading-pod_2025_june_bau_tm-1374626-jun25-bau-no1custard_jcr_content_library-par_referenced-component_icons_brandIcon_brandImage", "uniqueId": "_content_waitrosegroceriescms_en_library_productGrid_static-trading-pod_2025_june_bau_tm-1374626-jun25-bau-no1custard_jcr_content_library-par_referenced-component_icons_brandIcon_brandImage", "childComponents": [], "nodeName": "brandImage", "componentPlaceholder": false, "styleIds": [], "adaptiveSrcs": {}, "uncropped": false, "isDecorative": false, "analytics": {"promoName": "waitrose:other", "assetModuleType": "Other", "enhancedEcommerceInternalPromotion": false}, "newWindow": false, "mobileImage": {}, "childComponentsVerticalAlignment": "top", "overlayColor": "", "tabletImage": {}, ":items": {}, ":itemsOrder": []}, "position": "floated"}, "offerRoundel": {"display": false, "image": {"multiService": false, "multiServiceData": {}, "resourceType": "waitrosegroceriescms/components/content/image", "componentId": "_content_waitrosegroceriescms_en_library_productGrid_static-trading-pod_2025_june_bau_tm-1374626-jun25-bau-no1custard_jcr_content_library-par_referenced-component_icons_offerRoundel_roundelImage", "uniqueId": "_content_waitrosegroceriescms_en_library_productGrid_static-trading-pod_2025_june_bau_tm-1374626-jun25-bau-no1custard_jcr_content_library-par_referenced-component_icons_offerRoundel_roundelImage", "childComponents": [], "nodeName": "roundelImage", "componentPlaceholder": false, "styleIds": [], "src": "/content/waitrosegroceriescms/en/library/productGrid/static-trading-pod/2025/june/bau/tm-1374626-jun25-bau-no1custard/jcr:content/library-par/referenced-component/icons/offerRoundel/roundelImage.wtrAdaptiveImg.png/1749642885479.png", "adaptiveSrcs": {}, "altText": "Save up to \u00a320", "uncropped": false, "isDecorative": false, "fileReference": "/content/dam/waitrosegroceriescms/icons/offerroundels/SAVE-up-to-20pounds.png", "dynamicImages": {"highQuality90": "https://waitrose-prod.scene7.com/is/image/waitroseprod/SAVE-up-to-20pounds?uuid=0d099660-ce62-4b23-bcec-b35880b89084&$Waitrose-Image-Preset-90$", "highQuality100": "https://waitrose-prod.scene7.com/is/image/waitroseprod/SAVE-up-to-20pounds?uuid=0d099660-ce62-4b23-bcec-b35880b89084&$Waitrose-Image-Preset-100$", "highQuality": "https://waitrose-prod.scene7.com/is/image/waitroseprod/SAVE-up-to-20pounds?uuid=0d099660-ce62-4b23-bcec-b35880b89084&$Waitrose-High-Quality-Image-Preset$", "defaultQuality": "https://waitrose-prod.scene7.com/is/image/waitroseprod/SAVE-up-to-20pounds?uuid=0d099660-ce62-4b23-bcec-b35880b89084&$Waitrose-Default-Image-Preset$", "highQuality85": "https://waitrose-prod.scene7.com/is/image/waitroseprod/SAVE-up-to-20pounds?uuid=0d099660-ce62-4b23-bcec-b35880b89084&$Waitrose-Image-Preset-85$", "highQuality95": "https://waitrose-prod.scene7.com/is/image/waitroseprod/SAVE-up-to-20pounds?uuid=0d099660-ce62-4b23-bcec-b35880b89084&$Waitrose-Image-Preset-95$"}, "analytics": {"promoName": "waitrose:other", "assetModuleType": "Other", "enhancedEcommerceInternalPromotion": false}, "newWindow": false, "mobileImage": {}, "childComponentsVerticalAlignment": "top", "overlayColor": "", "tabletImage": {}, "assetMetadataWidth": "113", "assetMetadataHeight": "113", ":items": {}, ":itemsOrder": []}}}, "analytics": {"analyticsId": "_content_waitrosegroceriescms_en_library_productGrid_static-trading-pod_2025_june_bau_tm-1374626-jun25-bau-no1custard_jcr_content_library-par_referenced-component", "analyticsComponentType": "waitrosegroceriescms/components/content/tradingcontent/tradingcell", "promoName": "Merch_No1Custard_Try_TM_MPFDE_DAIRY_CREAMANDSEASONALBUTTERS_P7_Fresh_2025"}, ":items": {}, ":itemsOrder": []}}, {"__typename": "GridProduct", "searchProduct": {"adTechSponsoredPosition": null, "brand": "Waitrose Ltd", "categories": [{"name": "Groceries", "id": "10051"}, {"name": "Frozen", "id": "300000"}, {"name": "Frozen Fruits & Smoothie Mixes", "id": "300010"}, {"name": "Fruit Mix", "id": "300061"}], "cqResponsive": {"deviceBreakpoints": [{"name": "default", "visible": true, "width": "2"}, {"name": "lg", "visible": true, "width": "3"}, {"name": "md", "visible": true, "width": "4"}, {"name": "sm", "visible": true, "width": "4"}, {"name": "xs", "visible": true, "width": "12"}]}, "crealytics": null, "currentSaleUnitPrice": {"price": {"amount": 2.9, "currencyCode": "GBP"}, "quantity": {"amount": 1, "uom": "C62"}}, "defaultQuantity": {"uom": "C62"}, "depositCharge": null, "displayPrice": "\u00a32.90", "displayPriceEstimated": false, "displayPriceQualifier": "\u00a36.05/kg", "formattedWeightRange": null, "formattedPriceRange": null, "id": "568900-138033-138034", "leadTime": 0, "lineNumber": "568900", "maxPersonalisedMessageLength": 0, "name": "LoveLife Frozen Strawberry & Banana Smoothie Mix", "markedForDelete": false, "persistDefault": true, "productImageUrls": {"extraLarge": "https://ecom-su-static-prod.wtrecom.com/images/products/4/LN_568900_BP_4.jpg", "large": "https://ecom-su-static-prod.wtrecom.com/images/products/11/LN_568900_BP_11.jpg", "medium": "https://ecom-su-static-prod.wtrecom.com/images/products/3/LN_568900_BP_3.jpg", "small": "https://ecom-su-static-prod.wtrecom.com/images/products/9/LN_568900_BP_9.jpg"}, "productType": "G", "promotion": null, "promotions": [], "restriction": {"availableDates": []}, "resultType": "GENERAL", "reviews": {"averageRating": 4.1143, "reviewCount": 35}, "size": "480g", "sponsored": false, "sponsorshipId": null, "substitutionsProhibited": false, "thumbnail": "https://ecom-su-static-prod.wtrecom.com/images/products/9/LN_568900_BP_9.jpg", "typicalWeight": null, "servings": null, "weights": {"uoms": ["C62"], "pricePerUomQualifier": "\u00a36.05/kg", "perUomQualifier": null, "defaultQuantity": null, "servings": null, "sizeDescription": null}, "productTags": [{"name": "Frozen", "tooltip": null}], "marketingBadges": null}}, {"__typename": "GridProduct", "searchProduct": {"adTechSponsoredPosition": null, "brand": "Waitrose Ltd", "categories": [{"name": "Groceries", "id": "10051"}, {"name": "Frozen", "id": "300000"}, {"name": "Frozen Fruits & Smoothie Mixes", "id": "300010"}, {"name": "Fruit Mix", "id": "300061"}], "cqResponsive": {"deviceBreakpoints": [{"name": "default", "visible": true, "width": "2"}, {"name": "lg", "visible": true, "width": "3"}, {"name": "md", "visible": true, "width": "4"}, {"name": "sm", "visible": true, "width": "4"}, {"name": "xs", "visible": true, "width": "12"}]}, "crealytics": null, "currentSaleUnitPrice": {"price": {"amount": 2.9, "currencyCode": "GBP"}, "quantity": {"amount": 1, "uom": "C62"}}, "defaultQuantity": {"uom": "C62"}, "depositCharge": null, "displayPrice": "\u00a32.90", "displayPriceEstimated": false, "displayPriceQualifier": "\u00a36.05/kg", "formattedWeightRange": null, "formattedPriceRange": null, "id": "363619-137891-137892", "leadTime": 0, "lineNumber": "363619", "maxPersonalisedMessageLength": 0, "name": "LoveLife Frozen Tropical Smoothie Mix", "markedForDelete": false, "persistDefault": true, "productImageUrls": {"extraLarge": "https://ecom-su-static-prod.wtrecom.com/images/products/4/LN_363619_BP_4.jpg", "large": "https://ecom-su-static-prod.wtrecom.com/images/products/11/LN_363619_BP_11.jpg", "medium": "https://ecom-su-static-prod.wtrecom.com/images/products/3/LN_363619_BP_3.jpg", "small": "https://ecom-su-static-prod.wtrecom.com/images/products/9/LN_363619_BP_9.jpg"}, "productType": "G", "promotion": null, "promotions": [], "restriction": {"availableDates": []}, "resultType": "GENERAL", "reviews": {"averageRating": 4, "reviewCount": 20}, "size": "480g", "sponsored": false, "sponsorshipId": null, "substitutionsProhibited": false, "thumbnail": "https://ecom-su-static-prod.wtrecom.com/images/products/9/LN_363619_BP_9.jpg", "typicalWeight": null, "servings": null, "weights": {"uoms": ["C62"], "pricePerUomQualifier": "\u00a36.05/kg", "perUomQualifier": null, "defaultQuantity": null, "servings": null, "sizeDescription": null}, "productTags": [{"name": "Frozen", "tooltip": null}], "marketingBadges": null}}, {"__typename": "GridProduct", "searchProduct": {"adTechSponsoredPosition": null, "brand": "Tr\u00fc Fr\u00fc", "categories": [{"name": "Groceries", "id": "10051"}, {"name": "Frozen", "id": "300000"}, {"name": "Ice Cream, Frozen Yogurt & Sorbets", "id": "300011"}, {"name": "Mini Ice Cream Tubs, Sticks & Bites", "id": "30730942-8361-4933-aa30-a8ccd020b232"}], "cqResponsive": {"deviceBreakpoints": [{"name": "default", "visible": true, "width": "2"}, {"name": "lg", "visible": true, "width": "3"}, {"name": "md", "visible": true, "width": "4"}, {"name": "sm", "visible": true, "width": "4"}, {"name": "xs", "visible": true, "width": "12"}]}, "crealytics": null, "currentSaleUnitPrice": {"price": {"amount": 6, "currencyCode": "GBP"}, "quantity": {"amount": 1, "uom": "C62"}}, "defaultQuantity": {"uom": "C62"}, "depositCharge": null, "displayPrice": "\u00a34.50", "displayPriceEstimated": false, "displayPriceQualifier": "\u00a322.50/kg", "formattedWeightRange": null, "formattedPriceRange": null, "id": "884206-843582-843583", "leadTime": 0, "lineNumber": "884206", "maxPersonalisedMessageLength": 0, "name": "TruFru Blueberries White & Dark Chocolate", "markedForDelete": false, "persistDefault": true, "productImageUrls": {"extraLarge": "https://ecom-su-static-prod.wtrecom.com/images/products/4/LN_884206_BP_4.jpg", "large": "https://ecom-su-static-prod.wtrecom.com/images/products/11/LN_884206_BP_11.jpg", "medium": "https://ecom-su-static-prod.wtrecom.com/images/products/3/LN_884206_BP_3.jpg", "small": "https://ecom-su-static-prod.wtrecom.com/images/products/9/LN_884206_BP_9.jpg"}, "productType": "G", "promotion": {"discount": null, "groups": [{"threshold": 1, "name": "X", "lineNumbers": ["710537", "918763", "884206", "937607"]}], "hidden": null, "myWaitrosePromotion": false, "promotionDescription": "Save \u00a31.50", "promotionId": 507916, "promotionTypeCode": "WN", "wasDisplayPrice": null}, "promotions": [{"discount": null, "groups": [{"threshold": 1, "name": "X", "lineNumbers": ["710537", "918763", "884206", "937607"]}], "hidden": null, "myWaitrosePromotion": false, "promotionDescription": "Save \u00a31.50", "promotionId": 507916, "promotionTypeCode": "WN", "wasDisplayPrice": null}], "restriction": {"availableDates": []}, "resultType": "GENERAL", "reviews": {"averageRating": 4.875, "reviewCount": 8}, "size": "200g", "sponsored": false, "sponsorshipId": null, "substitutionsProhibited": false, "thumbnail": "https://ecom-su-static-prod.wtrecom.com/images/products/9/LN_884206_BP_9.jpg", "typicalWeight": null, "servings": null, "weights": {"uoms": ["C62"], "pricePerUomQualifier": "\u00a322.50/kg", "perUomQualifier": null, "defaultQuantity": null, "servings": null, "sizeDescription": null}, "productTags": [{"name": "Frozen", "tooltip": null}], "marketingBadges": [{"name": "Exclusive"}]}}, {"__typename": "GridProduct", "searchProduct": {"adTechSponsoredPosition": null, "brand": "Tr\u00fc Fr\u00fc", "categories": [{"name": "Groceries", "id": "10051"}, {"name": "Frozen", "id": "300000"}, {"name": "Ice Cream, Frozen Yogurt & Sorbets", "id": "300011"}, {"name": "Mini Ice Cream Tubs, Sticks & Bites", "id": "30730942-8361-4933-aa30-a8ccd020b232"}], "cqResponsive": {"deviceBreakpoints": [{"name": "default", "visible": true, "width": "2"}, {"name": "lg", "visible": true, "width": "3"}, {"name": "md", "visible": true, "width": "4"}, {"name": "sm", "visible": true, "width": "4"}, {"name": "xs", "visible": true, "width": "12"}]}, "crealytics": null, "currentSaleUnitPrice": {"price": {"amount": 6, "currencyCode": "GBP"}, "quantity": {"amount": 1, "uom": "C62"}}, "defaultQuantity": {"uom": "C62"}, "depositCharge": null, "displayPrice": "\u00a34.50", "displayPriceEstimated": false, "displayPriceQualifier": "\u00a322.50/kg", "formattedWeightRange": null, "formattedPriceRange": null, "id": "918763-843640-843641", "leadTime": 0, "lineNumber": "918763", "maxPersonalisedMessageLength": 0, "name": "TruFru Pina Colada Pineapple White Chocolate & Coconut", "markedForDelete": false, "persistDefault": true, "productImageUrls": {"extraLarge": "https://ecom-su-static-prod.wtrecom.com/images/products/4/LN_918763_BP_4.jpg", "large": "https://ecom-su-static-prod.wtrecom.com/images/products/11/LN_918763_BP_11.jpg", "medium": "https://ecom-su-static-prod.wtrecom.com/images/products/3/LN_918763_BP_3.jpg", "small": "https://ecom-su-static-prod.wtrecom.com/images/products/9/LN_918763_BP_9.jpg"}, "productType": "G", "promotion": {"discount": null, "groups": [{"threshold": 1, "name": "X", "lineNumbers": ["710537", "918763", "884206", "937607"]}], "hidden": null, "myWaitrosePromotion": false, "promotionDescription": "Save \u00a31.50", "promotionId": 507916, "promotionTypeCode": "WN", "wasDisplayPrice": null}, "promotions": [{"discount": null, "groups": [{"threshold": 1, "name": "X", "lineNumbers": ["710537", "918763", "884206", "937607"]}], "hidden": null, "myWaitrosePromotion": false, "promotionDescription": "Save \u00a31.50", "promotionId": 507916, "promotionTypeCode": "WN", "wasDisplayPrice": null}], "restriction": {"availableDates": []}, "resultType": "GENERAL", "reviews": {"averageRating": 3.3333, "reviewCount": 6}, "size": "200g", "sponsored": false, "sponsorshipId": null, "substitutionsProhibited": false, "thumbnail": "https://ecom-su-static-prod.wtrecom.com/images/products/9/LN_918763_BP_9.jpg", "typicalWeight": null, "servings": null, "weights": {"uoms": ["C62"], "pricePerUomQualifier": "\u00a322.50/kg", "perUomQualifier": null, "defaultQuantity": null, "servings": null, "sizeDescription": null}, "productTags": [{"name": "Frozen", "tooltip": null}], "marketingBadges": []}}, {"__typename": "GridProduct", "searchProduct": {"adTechSponsoredPosition": null, "brand": "Tr\u00fc Fr\u00fc", "categories": [{"name": "Groceries", "id": "10051"}, {"name": "Frozen", "id": "300000"}, {"name": "Ice Cream, Frozen Yogurt & Sorbets", "id": "300011"}, {"name": "Mini Ice Cream Tubs, Sticks & Bites", "id": "30730942-8361-4933-aa30-a8ccd020b232"}], "cqResponsive": {"deviceBreakpoints": [{"name": "default", "visible": true, "width": "2"}, {"name": "lg", "visible": true, "width": "3"}, {"name": "md", "visible": true, "width": "4"}, {"name": "sm", "visible": true, "width": "4"}, {"name": "xs", "visible": true, "width": "12"}]}, "crealytics": null, "currentSaleUnitPrice": {"price": {"amount": 6, "currencyCode": "GBP"}, "quantity": {"amount": 1, "uom": "C62"}}, "defaultQuantity": {"uom": "C62"}, "depositCharge": null, "displayPrice": "\u00a34.50", "displayPriceEstimated": false, "displayPriceQualifier": "\u00a322.50/kg", "formattedWeightRange": null, "formattedPriceRange": null, "id": "937607-843690-843691", "leadTime": 0, "lineNumber": "937607", "maxPersonalisedMessageLength": 0, "name": "TruFru Raspberries White & Dark Chocolate", "markedForDelete": false, "persistDefault": true, "productImageUrls": {"extraLarge": "https://ecom-su-static-prod.wtrecom.com/images/products/4/LN_937607_BP_4.jpg", "large": "https://ecom-su-static-prod.wtrecom.com/images/products/11/LN_937607_BP_11.jpg", "medium": "https://ecom-su-static-prod.wtrecom.com/images/products/3/LN_937607_BP_3.jpg", "small": "https://ecom-su-static-prod.wtrecom.com/images/products/9/LN_937607_BP_9.jpg"}, "productType": "G", "promotion": {"discount": null, "groups": [{"threshold": 1, "name": "X", "lineNumbers": ["710537", "918763", "884206", "937607"]}], "hidden": null, "myWaitrosePromotion": false, "promotionDescription": "Save \u00a31.50", "promotionId": 507916, "promotionTypeCode": "WN", "wasDisplayPrice": null}, "promotions": [{"discount": null, "groups": [{"threshold": 1, "name": "X", "lineNumbers": ["710537", "918763", "884206", "937607"]}], "hidden": null, "myWaitrosePromotion": false, "promotionDescription": "Save \u00a31.50", "promotionId": 507916, "promotionTypeCode": "WN", "wasDisplayPrice": null}], "restriction": {"availableDates": []}, "resultType": "GENERAL", "reviews": {"averageRating": 4.6667, "reviewCount": 15}, "size": "200g", "sponsored": false, "sponsorshipId": null, "substitutionsProhibited": false, "thumbnail": "https://ecom-su-static-prod.wtrecom.com/images/products/9/LN_937607_BP_9.jpg", "typicalWeight": null, "servings": null, "weights": {"uoms": ["C62"], "pricePerUomQualifier": "\u00a322.50/kg", "perUomQualifier": null, "defaultQuantity": null, "servings": null, "sizeDescription": null}, "productTags": [{"name": "Frozen", "tooltip": null}], "marketingBadges": []}}, {"__typename": "GridProduct", "searchProduct": {"adTechSponsoredPosition": null, "brand": "Tr\u00fc Fr\u00fc", "categories": [{"name": "Groceries", "id": "10051"}, {"name": "Frozen", "id": "300000"}, {"name": "Ice Cream, Frozen Yogurt & Sorbets", "id": "300011"}, {"name": "Mini Ice Cream Tubs, Sticks & Bites", "id": "30730942-8361-4933-aa30-a8ccd020b232"}], "cqResponsive": {"deviceBreakpoints": [{"name": "default", "visible": true, "width": "2"}, {"name": "lg", "visible": true, "width": "3"}, {"name": "md", "visible": true, "width": "4"}, {"name": "sm", "visible": true, "width": "4"}, {"name": "xs", "visible": true, "width": "12"}]}, "crealytics": null, "currentSaleUnitPrice": {"price": {"amount": 6, "currencyCode": "GBP"}, "quantity": {"amount": 1, "uom": "C62"}}, "defaultQuantity": {"uom": "C62"}, "depositCharge": null, "displayPrice": "\u00a34.50", "displayPriceEstimated": false, "displayPriceQualifier": "\u00a322.50/kg", "formattedWeightRange": null, "formattedPriceRange": null, "id": "710537-843572-843573", "leadTime": 0, "lineNumber": "710537", "maxPersonalisedMessageLength": 0, "name": "TruFru Strawberries White & Milk Chocolate", "markedForDelete": false, "persistDefault": true, "productImageUrls": {"extraLarge": "https://ecom-su-static-prod.wtrecom.com/images/products/4/LN_710537_BP_4.jpg", "large": "https://ecom-su-static-prod.wtrecom.com/images/products/11/LN_710537_BP_11.jpg", "medium": "https://ecom-su-static-prod.wtrecom.com/images/products/3/LN_710537_BP_3.jpg", "small": "https://ecom-su-static-prod.wtrecom.com/images/products/9/LN_710537_BP_9.jpg"}, "productType": "G", "promotion": {"discount": null, "groups": [{"threshold": 1, "name": "X", "lineNumbers": ["710537", "918763", "884206", "937607"]}], "hidden": null, "myWaitrosePromotion": false, "promotionDescription": "Save \u00a31.50", "promotionId": 507916, "promotionTypeCode": "WN", "wasDisplayPrice": null}, "promotions": [{"discount": null, "groups": [{"threshold": 1, "name": "X", "lineNumbers": ["710537", "918763", "884206", "937607"]}], "hidden": null, "myWaitrosePromotion": false, "promotionDescription": "Save \u00a31.50", "promotionId": 507916, "promotionTypeCode": "WN", "wasDisplayPrice": null}], "restriction": {"availableDates": []}, "resultType": "GENERAL", "reviews": {"averageRating": 4.2941, "reviewCount": 17}, "size": "200g", "sponsored": false, "sponsorshipId": null, "substitutionsProhibited": false, "thumbnail": "https://ecom-su-static-prod.wtrecom.com/images/products/9/LN_710537_BP_9.jpg", "typicalWeight": null, "servings": null, "weights": {"uoms": ["C62"], "pricePerUomQualifier": "\u00a322.50/kg", "perUomQualifier": null, "defaultQuantity": null, "servings": null, "sizeDescription": null}, "productTags": [{"name": "Frozen", "tooltip": null}], "marketingBadges": []}}, {"__typename": "GridProduct", "searchProduct": {"adTechSponsoredPosition": null, "brand": "Waitrose Ltd", "categories": [{"name": "Groceries", "id": "10051"}, {"name": "Frozen", "id": "300000"}, {"name": "Frozen Fruits & Smoothie Mixes", "id": "300010"}, {"name": "Fruit Mix", "id": "300061"}], "cqResponsive": {"deviceBreakpoints": [{"name": "default", "visible": true, "width": "2"}, {"name": "lg", "visible": true, "width": "3"}, {"name": "md", "visible": true, "width": "4"}, {"name": "sm", "visible": true, "width": "4"}, {"name": "xs", "visible": true, "width": "12"}]}, "crealytics": null, "currentSaleUnitPrice": {"price": {"amount": 3.5, "currencyCode": "GBP"}, "quantity": {"amount": 1, "uom": "C62"}}, "defaultQuantity": {"uom": "C62"}, "depositCharge": null, "displayPrice": "\u00a33.50", "displayPriceEstimated": false, "displayPriceQualifier": "\u00a311.67/kg", "formattedWeightRange": null, "formattedPriceRange": null, "id": "512337-72411-72412", "leadTime": 0, "lineNumber": "512337", "maxPersonalisedMessageLength": 0, "name": "Waitrose Frozen British Blackberries", "markedForDelete": false, "persistDefault": true, "productImageUrls": {"extraLarge": "https://ecom-su-static-prod.wtrecom.com/images/products/4/LN_512337_BP_4.jpg", "large": "https://ecom-su-static-prod.wtrecom.com/images/products/11/LN_512337_BP_11.jpg", "medium": "https://ecom-su-static-prod.wtrecom.com/images/products/3/LN_512337_BP_3.jpg", "small": "https://ecom-su-static-prod.wtrecom.com/images/products/9/LN_512337_BP_9.jpg"}, "productType": "G", "promotion": null, "promotions": [], "restriction": {"availableDates": []}, "resultType": "GENERAL", "reviews": {"averageRating": 4.3462, "reviewCount": 78}, "size": "300g", "sponsored": false, "sponsorshipId": null, "substitutionsProhibited": false, "thumbnail": "https://ecom-su-static-prod.wtrecom.com/images/products/9/LN_512337_BP_9.jpg", "typicalWeight": null, "servings": null, "weights": {"uoms": ["C62"], "pricePerUomQualifier": "\u00a39.34/kg", "perUomQualifier": null, "defaultQuantity": null, "servings": null, "sizeDescription": null}, "productTags": [{"name": "Frozen", "tooltip": null}, {"name": "British", "tooltip": null}], "marketingBadges": null}}, {"__typename": "GridProduct", "searchProduct": {"adTechSponsoredPosition": null, "brand": "Waitrose Ltd", "categories": [{"name": "Groceries", "id": "10051"}, {"name": "Frozen", "id": "300000"}, {"name": "Frozen Fruits & Smoothie Mixes", "id": "300010"}, {"name": "Raspberry", "id": "300060"}], "cqResponsive": {"deviceBreakpoints": [{"name": "default", "visible": true, "width": "2"}, {"name": "lg", "visible": true, "width": "3"}, {"name": "md", "visible": true, "width": "4"}, {"name": "sm", "visible": true, "width": "4"}, {"name": "xs", "visible": true, "width": "12"}]}, "crealytics": null, "currentSaleUnitPrice": {"price": {"amount": 3.8, "currencyCode": "GBP"}, "quantity": {"amount": 1, "uom": "C62"}}, "defaultQuantity": {"uom": "C62"}, "depositCharge": null, "displayPrice": "\u00a33.80", "displayPriceEstimated": false, "displayPriceQualifier": "\u00a312.67/kg", "formattedWeightRange": null, "formattedPriceRange": null, "id": "055339-27779-27780", "leadTime": 0, "lineNumber": "055339", "maxPersonalisedMessageLength": 0, "name": "Waitrose Frozen British Raspberries", "markedForDelete": false, "persistDefault": true, "productImageUrls": {"extraLarge": "https://ecom-su-static-prod.wtrecom.com/images/products/4/LN_055339_BP_4.jpg", "large": "https://ecom-su-static-prod.wtrecom.com/images/products/11/LN_055339_BP_11.jpg", "medium": "https://ecom-su-static-prod.wtrecom.com/images/products/3/LN_055339_BP_3.jpg", "small": "https://ecom-su-static-prod.wtrecom.com/images/products/9/LN_055339_BP_9.jpg"}, "productType": "G", "promotion": null, "promotions": [], "restriction": {"availableDates": []}, "resultType": "GENERAL", "reviews": {"averageRating": 4.3819, "reviewCount": 144}, "size": "300g", "sponsored": false, "sponsorshipId": null, "substitutionsProhibited": false, "thumbnail": "https://ecom-su-static-prod.wtrecom.com/images/products/9/LN_055339_BP_9.jpg", "typicalWeight": null, "servings": null, "weights": {"uoms": ["C62"], "pricePerUomQualifier": "\u00a39.34/kg", "perUomQualifier": null, "defaultQuantity": null, "servings": null, "sizeDescription": null}, "productTags": [{"name": "Frozen", "tooltip": null}, {"name": "British", "tooltip": null}], "marketingBadges": null}}, {"__typename": "GridProduct", "searchProduct": {"adTechSponsoredPosition": null, "brand": "Waitrose Ltd", "categories": [{"name": "Groceries", "id": "10051"}, {"name": "Frozen", "id": "300000"}, {"name": "Frozen Fruits & Smoothie Mixes", "id": "300010"}, {"name": "Fruit Mix", "id": "300061"}], "cqResponsive": {"deviceBreakpoints": [{"name": "default", "visible": true, "width": "2"}, {"name": "lg", "visible": true, "width": "3"}, {"name": "md", "visible": true, "width": "4"}, {"name": "sm", "visible": true, "width": "4"}, {"name": "xs", "visible": true, "width": "12"}]}, "crealytics": null, "currentSaleUnitPrice": {"price": {"amount": 3.8, "currencyCode": "GBP"}, "quantity": {"amount": 1, "uom": "C62"}}, "defaultQuantity": {"uom": "C62"}, "depositCharge": null, "displayPrice": "\u00a33.80", "displayPriceEstimated": false, "displayPriceQualifier": "\u00a312.67/kg", "formattedWeightRange": null, "formattedPriceRange": null, "id": "010464-5228-5229", "leadTime": 0, "lineNumber": "010464", "maxPersonalisedMessageLength": 0, "name": "Waitrose Frozen British Summer Fruits", "markedForDelete": false, "persistDefault": true, "productImageUrls": {"extraLarge": "https://ecom-su-static-prod.wtrecom.com/images/products/4/LN_010464_BP_4.jpg", "large": "https://ecom-su-static-prod.wtrecom.com/images/products/11/LN_010464_BP_11.jpg", "medium": "https://ecom-su-static-prod.wtrecom.com/images/products/3/LN_010464_BP_3.jpg", "small": "https://ecom-su-static-prod.wtrecom.com/images/products/9/LN_010464_BP_9.jpg"}, "productType": "G", "promotion": null, "promotions": [], "restriction": {"availableDates": []}, "resultType": "GENERAL", "reviews": {"averageRating": 4.8, "reviewCount": 75}, "size": "300g", "sponsored": false, "sponsorshipId": null, "substitutionsProhibited": false, "thumbnail": "https://ecom-su-static-prod.wtrecom.com/images/products/9/LN_010464_BP_9.jpg", "typicalWeight": null, "servings": null, "weights": {"uoms": ["C62"], "pricePerUomQualifier": "\u00a39.34/kg", "perUomQualifier": null, "defaultQuantity": null, "servings": null, "sizeDescription": null}, "productTags": [{"name": "Frozen", "tooltip": null}, {"name": "British", "tooltip": null}], "marketingBadges": null}}, {"__typename": "GridProduct", "searchProduct": {"adTechSponsoredPosition": null, "brand": "Waitrose Ltd", "categories": [{"name": "Groceries", "id": "10051"}, {"name": "Frozen", "id": "300000"}, {"name": "Frozen Fruits & Smoothie Mixes", "id": "300010"}, {"name": "Fruit Mix", "id": "300061"}], "cqResponsive": {"deviceBreakpoints": [{"name": "default", "visible": true, "width": "2"}, {"name": "lg", "visible": true, "width": "3"}, {"name": "md", "visible": true, "width": "4"}, {"name": "sm", "visible": true, "width": "4"}, {"name": "xs", "visible": true, "width": "12"}]}, "crealytics": null, "currentSaleUnitPrice": {"price": {"amount": 2.65, "currencyCode": "GBP"}, "quantity": {"amount": 1, "uom": "C62"}}, "defaultQuantity": {"uom": "C62"}, "depositCharge": null, "displayPrice": "\u00a32.65", "displayPriceEstimated": false, "displayPriceQualifier": "\u00a35.89/kg", "formattedWeightRange": null, "formattedPriceRange": null, "id": "500603-70743-70744", "leadTime": 0, "lineNumber": "500603", "maxPersonalisedMessageLength": 0, "name": "Waitrose Frozen Forest Fruit Mix", "markedForDelete": false, "persistDefault": true, "productImageUrls": {"extraLarge": "https://ecom-su-static-prod.wtrecom.com/images/products/4/LN_500603_BP_4.jpg", "large": "https://ecom-su-static-prod.wtrecom.com/images/products/11/LN_500603_BP_11.jpg", "medium": "https://ecom-su-static-prod.wtrecom.com/images/products/3/LN_500603_BP_3.jpg", "small": "https://ecom-su-static-prod.wtrecom.com/images/products/9/LN_500603_BP_9.jpg"}, "productType": "G", "promotion": null, "promotions": [], "restriction": {"availableDates": []}, "resultType": "GENERAL", "reviews": {"averageRating": 4.3617, "reviewCount": 94}, "size": "450g", "sponsored": false, "sponsorshipId": null, "substitutionsProhibited": false, "thumbnail": "https://ecom-su-static-prod.wtrecom.com/images/products/9/LN_500603_BP_9.jpg", "typicalWeight": null, "servings": null, "weights": {"uoms": ["C62"], "pricePerUomQualifier": "\u00a35.89/kg", "perUomQualifier": null, "defaultQuantity": null, "servings": null, "sizeDescription": null}, "productTags": [{"name": "Frozen", "tooltip": null}], "marketingBadges": null}}, {"__typename": "GridProduct", "searchProduct": {"adTechSponsoredPosition": null, "brand": "Waitrose Ltd", "categories": [{"name": "Groceries", "id": "10051"}, {"name": "Frozen", "id": "300000"}, {"name": "Frozen Fruits & Smoothie Mixes", "id": "300010"}, {"name": "Fruit Mix", "id": "300061"}], "cqResponsive": {"deviceBreakpoints": [{"name": "default", "visible": true, "width": "2"}, {"name": "lg", "visible": true, "width": "3"}, {"name": "md", "visible": true, "width": "4"}, {"name": "sm", "visible": true, "width": "4"}, {"name": "xs", "visible": true, "width": "12"}]}, "crealytics": null, "currentSaleUnitPrice": {"price": {"amount": 2.9, "currencyCode": "GBP"}, "quantity": {"amount": 1, "uom": "C62"}}, "defaultQuantity": {"uom": "C62"}, "depositCharge": null, "displayPrice": "\u00a32.90", "displayPriceEstimated": false, "displayPriceQualifier": "\u00a36.05/kg", "formattedWeightRange": null, "formattedPriceRange": null, "id": "764484-138151-138152", "leadTime": 0, "lineNumber": "764484", "maxPersonalisedMessageLength": 0, "name": "Waitrose LoveLife Frozen Berry Smoothie Mix", "markedForDelete": false, "persistDefault": true, "productImageUrls": {"extraLarge": "https://ecom-su-static-prod.wtrecom.com/images/products/4/LN_764484_BP_4.jpg", "large": "https://ecom-su-static-prod.wtrecom.com/images/products/11/LN_764484_BP_11.jpg", "medium": "https://ecom-su-static-prod.wtrecom.com/images/products/3/LN_764484_BP_3.jpg", "small": "https://ecom-su-static-prod.wtrecom.com/images/products/9/LN_764484_BP_9.jpg"}, "productType": "G", "promotion": null, "promotions": [], "restriction": {"availableDates": []}, "resultType": "GENERAL", "reviews": {"averageRating": 4.6061, "reviewCount": 33}, "size": "480g", "sponsored": false, "sponsorshipId": null, "substitutionsProhibited": false, "thumbnail": "https://ecom-su-static-prod.wtrecom.com/images/products/9/LN_764484_BP_9.jpg", "typicalWeight": null, "servings": null, "weights": {"uoms": ["C62"], "pricePerUomQualifier": "\u00a36.05/kg", "perUomQualifier": null, "defaultQuantity": null, "servings": null, "sizeDescription": null}, "productTags": [{"name": "Frozen", "tooltip": null}], "marketingBadges": null}}]}]